lambda3_memory_dft-1.0.2.dist-info/licenses/LICENSE
memory_dft/__init__.py
memory_dft/__main__.py
memory_dft/core/__init__.py
memory_dft/core/environment_operators.py
memory_dft/core/history_manager.py
memory_dft/core/material_failure.py
memory_dft/core/memory_kernel.py
memory_dft/core/sparse_engine_unified.py
memory_dft/engineering/__init__.py
memory_dft/engineering/thermo_mechanical_solver.py
memory_dft/holographic/__init__.py
memory_dft/holographic/dual.py
memory_dft/holographic/measurement.py
memory_dft/interfaces/__init__.py
memory_dft/interfaces/pyscf_interface.py
memory_dft/physics/__init__.py
memory_dft/physics/lambda3_bridge.py
memory_dft/physics/rdm.py
memory_dft/physics/topology.py
memory_dft/physics/vorticity.py
memory_dft/solvers/__init__.py
memory_dft/solvers/dse_solver.py
memory_dft/solvers/memory_indicators.py
memory_dft/solvers/thermal_holographic.py
memory_dft/tests/conftest.py
memory_dft/tests/test_smoke.py
lambda3_memory_dft-1.0.2.dist-info/METADATA
lambda3_memory_dft-1.0.2.dist-info/WHEEL
lambda3_memory_dft-1.0.2.dist-info/entry_points.txt
lambda3_memory_dft-1.0.2.dist-info/top_level.txt
lambda3_memory_dft-1.0.2.dist-info/RECORD
