Metadata-Version: 2.4
Name: lambda3-memory-dft
Version: 1.0.2
Summary: Direct Schrödinger Evolution (DSE) - First-Principles History-Dependent Quantum Dynamics
Author: Tamaki Iizumi
Author-email: Masamichi Iizumi <m.iizumi@miosync.email>
License: MIT
Project-URL: Homepage, https://github.com/miosync-masa/lambda3-memory-dft
Project-URL: Documentation, https://github.com/miosync-masa/lambda3-memory-dft#readme
Project-URL: Repository, https://github.com/miosync-masa/lambda3-memory-dft.git
Project-URL: Issues, https://github.com/miosync-masa/lambda3-memory-dft/issues
Keywords: direct-schrodinger-evolution,DSE,density-functional-theory,DFT,memory-kernel,non-markovian,quantum-chemistry,materials-science,path-dependence,history-dependent
Classifier: Development Status :: 4 - Beta
Classifier: Intended Audience :: Science/Research
Classifier: Topic :: Scientific/Engineering :: Physics
Classifier: Topic :: Scientific/Engineering :: Chemistry
Classifier: License :: OSI Approved :: MIT License
Classifier: Programming Language :: Python :: 3
Classifier: Programming Language :: Python :: 3.9
Classifier: Programming Language :: Python :: 3.10
Classifier: Programming Language :: Python :: 3.11
Classifier: Programming Language :: Python :: 3.12
Classifier: Operating System :: OS Independent
Requires-Python: >=3.9
License-File: LICENSE
Requires-Dist: numpy>=1.20.0
Requires-Dist: scipy>=1.7.0
Requires-Dist: typer>=0.9.0
Provides-Extra: gpu
Requires-Dist: cupy>=10.0.0; extra == "gpu"
Provides-Extra: pyscf
Requires-Dist: pyscf>=2.0.0; extra == "pyscf"
Provides-Extra: full
Requires-Dist: cupy>=10.0.0; extra == "full"
Requires-Dist: pyscf>=2.0.0; extra == "full"
Requires-Dist: matplotlib>=3.5.0; extra == "full"
Provides-Extra: dev
Requires-Dist: pytest>=7.0.0; extra == "dev"
Requires-Dist: pytest-cov>=4.0.0; extra == "dev"
Requires-Dist: black>=23.0.0; extra == "dev"
Requires-Dist: isort>=5.12.0; extra == "dev"
Requires-Dist: flake8>=6.0.0; extra == "dev"
Requires-Dist: mypy>=1.0.0; extra == "dev"
Dynamic: license-file
